[
  {
    "serialNumber": "1",
    "requestId": "SY23042026",
    "clientProjectName": "EMAAR",
    "requestReceivedDate": "2026-04-23",
    "requestApprovedBy": "Sulabh Awasthi",
    "hrOwnerEmployeeNumber": "9123454054",
    "hrOwnerName": "Ankita",
    "businessOwnerEmployeeNumber": "",
    "businessOwnerName": "",
    "candidateName": "GAURAV PATEL",
    "mobileNumber": "123456718",
    "email": "ga500@gmail.com",
    "currentLocation": "Gurugram",
    "preferredLocation": "Gurugram",
    "noticePeriod": "Immediate joiner",
    "qualification": "BSC",
    "skillsLevel": "Level 1",
    "profilePost": "DSE L1",
    "certification": "",
    "totalExperience": "4 yrs",
    "relevantExperience": "4 yrs",
    "currentCompany": "Acma Computers Pvt. Ltd.",
    "currentCtc": "29,000",
    "expectedCtc": "33,000",
    "offeredCtc": "27,000",
    "profileSource": "INTERNAL",
    "profileReceiveDate": "2026-04-23",
    "internalScreeningDate": "2026-04-24",
    "profileSentToBusinessOwnerDate": "",
    "profileConnectWithClientDate": "2026-04-24",
    "clientInterviewDate": "2026-04-30",
    "feedbackDate": "2026-04-30",
    "internalStatus": "SELECTED",
    "clientFinalStatus": "SELECTED",
    "updatedToCandidateDate": "",
    "offeredDate": "",
    "reasonIfOfferNotAccepted": "",
    "agreedJoiningDate": "",
    "reasonIfNotJoined": "",
    "actualJoiningDate": "",
    "joiningDetailsSharedDate": "",
    "remarks": "finally got selected",
    "status": "ACTIVE",
    "id": "a3e1f2ee-a5c4-45af-a6e9-19dfd3c8512b",
    "createdAt": "2026-05-19T06:25:15.292Z",
    "updatedAt": "2026-05-19T06:25:15.292Z",
    "applicantPortalId": "APP-0001",
    "applicantUsername": "app-0001",
    "applicantPortalEnabled": false
  },
  {
    "serialNumber": "2",
    "requestId": "SY23052026",
    "clientProjectName": "NAYAKA",
    "requestReceivedDate": "2026-05-18",
    "requestApprovedBy": "Sulabh Awasthi",
    "hrOwnerEmployeeNumber": "9123454054",
    "hrOwnerName": "Ankita",
    "businessOwnerEmployeeNumber": "technosys labs private limited",
    "businessOwnerName": "technosys labs private limited",
    "candidateName": "piyush",
    "mobileNumber": "09045333333",
    "email": "piyush@gmail.com",
    "currentLocation": "Gurugram",
    "preferredLocation": "Gurugram",
    "noticePeriod": "Immediate joiner",
    "qualification": "B.tech",
    "skillsLevel": "Level 3",
    "profilePost": "SoftwareEngineer",
    "certification": "",
    "totalExperience": "2 yrs",
    "relevantExperience": "2 yrs",
    "currentCompany": "technosys labs private limited",
    "currentCtc": "9,500",
    "expectedCtc": "30,000",
    "offeredCtc": "27,000",
    "profileSource": "INTERNAL",
    "profileReceiveDate": "2026-05-18",
    "internalScreeningDate": "2026-05-19",
    "internalScreeningCleared": "YES",
    "profileSentToBusinessOwner": "NOT_APPLICABLE",
    "profileSentToBusinessOwnerDate": "2026-05-19",
    "profileConnectWithClientDate": "2026-05-19",
    "interviewedByClient": "YES",
    "clientInterviewDate": "2026-05-20",
    "feedbackDate": "2026-05-20",
    "internalStatus": "SELECTED",
    "clientFinalStatus": "SELECTED",
    "updatedToCandidateDate": "2026-05-20",
    "offeredDate": "2026-05-20",
    "offerAccepted": "YES",
    "reasonIfOfferNotAccepted": "",
    "agreedJoiningDate": "2026-05-21",
    "joined": "YES",
    "reasonIfNotJoined": "",
    "actualJoiningDate": "2026-05-21",
    "joiningDetailsSharedDate": "",
    "remarks": "zczczcc",
    "status": "ACTIVE",
    "id": "97f4080f-7dce-4160-bcc8-26cf7a69484b",
    "createdAt": "2026-05-21T05:44:40.301Z",
    "updatedAt": "2026-05-21T08:50:36.032Z",
    "applicantPortalId": "APP-0002",
    "applicantUsername": "app-0002",
    "applicantPortalEnabled": true,
    "applicantPasswordHash": "$2b$10$eiywEeTLoTyao.YtrYOxnuSr9x9C7ZGlS/gcNLui7Y/9lzj.ov4VC",
    "applicantInvitedAt": "2026-05-21T08:50:36.032Z",
    "applicantDocumentsSubmittedAt": ""
  },
  {
    "applicantPortalId": "APP-0003",
    "applicantUsername": "app-0003",
    "applicantPasswordHash": "$2b$10$eaeq1gblMVcd6QA6npdaC.d97B4WQYusixaJJd6JHX91847Kgmtt.",
    "applicantPortalEnabled": true,
    "applicantInvitedAt": "2026-05-21T11:56:53.594Z",
    "applicantDocumentsSubmittedAt": "2026-05-21T08:55:29.034Z",
    "serialNumber": "3",
    "requestId": "SY23062026",
    "clientProjectName": "NTPC",
    "requestReceivedDate": "",
    "requestApprovedBy": "Sulabh Awasthi",
    "hrOwnerEmployeeNumber": "9123454054",
    "hrOwnerName": "Ankita",
    "businessOwnerEmployeeNumber": "technosys labs private limited",
    "businessOwnerName": "technosys labs private limited",
    "candidateName": "Suraj Bisht",
    "mobileNumber": "09045335477",
    "email": "bisht6993@gmail.com",
    "currentLocation": "",
    "preferredLocation": "",
    "noticePeriod": "Immediate joiner",
    "qualification": "B.tech",
    "skillsLevel": "Level 3",
    "profilePost": "SoftwareEngineer",
    "certification": "",
    "totalExperience": "2 yrs",
    "relevantExperience": "2 yrs",
    "currentCompany": "",
    "currentCtc": "9,500",
    "expectedCtc": "30,000",
    "offeredCtc": "27,000",
    "profileSource": "INTERNAL",
    "profileReceiveDate": "",
    "internalScreeningDate": "",
    "profileSentToBusinessOwnerDate": "",
    "profileConnectWithClientDate": "",
    "clientInterviewDate": "",
    "feedbackDate": "",
    "internalStatus": "SELECTED",
    "clientFinalStatus": "SELECTED",
    "updatedToCandidateDate": "",
    "offeredDate": "2026-05-21",
    "offerAccepted": "YES",
    "reasonIfOfferNotAccepted": "",
    "agreedJoiningDate": "",
    "reasonIfNotJoined": "",
    "actualJoiningDate": "",
    "joiningDetailsSharedDate": "",
    "remarks": "selected",
    "status": "ACTIVE",
    "id": "c57f2277-ecaf-41dc-8c25-719861a2dfa4",
    "createdAt": "2026-05-21T08:52:54.228Z",
    "updatedAt": "2026-05-21T11:56:53.596Z"
  },
  {
    "applicantPortalId": "APP-0004",
    "applicantUsername": "app-0004",
    "applicantPasswordHash": "$2b$10$rMD30IdonNTTVbtWSJxB0.zW9kMp.RPpOy/e7Lu.XcVwoQmOaSxCC",
    "applicantPortalEnabled": true,
    "applicantInvitedAt": "2026-05-28T10:56:22.794Z",
    "applicantDocumentsSubmittedAt": "",
    "serialNumber": "4",
    "requestId": "",
    "clientProjectName": "",
    "requestReceivedDate": "",
    "requestApprovedBy": "",
    "hrOwnerEmployeeNumber": "",
    "hrOwnerName": "",
    "businessOwnerEmployeeNumber": "",
    "businessOwnerName": "",
    "candidateName": "vatslaya",
    "gender": "male",
    "dateOfBirth": "2026-05-14",
    "mobileNumber": "2828282828",
    "email": "vatsalyapathak89@gmail.com",
    "currentLocation": "delhi",
    "preferredLocation": "",
    "noticePeriod": "",
    "qualification": "",
    "skillsLevel": "",
    "profilePost": "DSE L1",
    "certification": "",
    "totalExperience": "",
    "relevantExperience": "",
    "currentCompany": "",
    "currentCtc": "15000",
    "expectedCtc": "40000",
    "offeredCtc": "",
    "profileReceiveDate": "",
    "internalScreeningDate": "",
    "profileSentToBusinessOwnerDate": "",
    "profileConnectWithClientDate": "",
    "clientInterviewDate": "",
    "feedbackDate": "",
    "updatedToCandidateDate": "",
    "offeredDate": "",
    "reasonIfOfferNotAccepted": "",
    "agreedJoiningDate": "",
    "reasonIfNotJoined": "",
    "actualJoiningDate": "",
    "joiningDetailsSharedDate": "",
    "remarks": "",
    "status": "ACTIVE",
    "id": "59fe4dac-cf45-4455-8004-515da5a9f963",
    "createdAt": "2026-05-28T10:46:58.375Z",
    "updatedAt": "2026-05-28T10:56:22.794Z"
  }
]